<?xml version="1.0" encoding="UTF-8"?>

<!--Automatically translated by Globalization Translator (https://github.com/wilinz/globalization-translator)-->
<resources>
  <string-array name="ad_showing_mode_keys"> 
    <item>ትሑዝ</item>  
    <item>ኣብ መዓልቲ ሓደ ግዜ ኣርእዩ</item> 
  </string-array>
  <string-array name="ad_types_keys"> 
    <item>ሓንደበት</item>  
    <item>ዜና</item>  
    <item>ማሕበራዊ ርክብ</item>  
    <item>ካርቱን</item>  
    <item>ጸወታ</item> 
  </string-array>
  <string-array name="root_record_out_file_type_keys"> 
    <item>ክእረም ዝኽእል js ፋይል</item>  
    <item>ዘይእረም ክልተኣዊ</item> 
  </string-array>
  <string-array name="keys_documentation_source"> 
    <item>ናይ ከባቢ ሰነዳት።</item>  
    <item>ብኢንተርነት ዝግበር ሰነዳት።</item> 
  </string-array>
</resources>
